langchain_naver_community/__init__.py
langchain_naver_community/tool.py
langchain_naver_community/utils.py
langchain_naver_community-0.1.1.dist-info/METADATA
langchain_naver_community-0.1.1.dist-info/WHEEL
langchain_naver_community-0.1.1.dist-info/licenses/LICENSE
langchain_naver_community-0.1.1.dist-info/RECORD
