Metadata-Version: 2.4
Name: langchain-naver-community
Version: 0.1.1
Summary: Add your description here
Project-URL: Repository, https://github.com/e7217/langchain-naver-community
License-File: LICENSE
Requires-Python: >=3.8
Requires-Dist: aiohttp>=3.10.11
Requires-Dist: langchain>=0.0.27
Requires-Dist: pydantic>=2.10.6
